events/__init__.py
events/core/__init__.py
events/core/broker.py
events/core/components/__init__.py
events/core/components/_base.py
events/core/components/publisher.py
events/core/components/subscriber.py
events/core/components/transceiver.py
events/core/decorators/__init__.py
events/core/decorators/_register.py
events/core/decorators/_utils.py
events/core/decorators/multiple.py
events/core/decorators/single.py
events/core/event/__init__.py
events/core/event/type.py
events/core/registry/__init__.py
events/core/registry/registration.py
events/decorators/__init__.py
events/state/__init__.py
events/state/decorators/__init__.py
events/state/decorators/initial_state.py
events/state/decorators/state.py
events/state/decorators/transitions.py
events/state/machine.py
cm_events-0.1.0.dist-info/LICENSE
cm_events-0.1.0.dist-info/METADATA
cm_events-0.1.0.dist-info/WHEEL
cm_events-0.1.0.dist-info/RECORD
