Metadata-Version: 2.3
Name: cm-events
Version: 0.1.0
Summary: Minimal async pub/sub package with decorators and state machines
License: MIT
Author: Carlos-Mesquita
Author-email: cmesquita1999@gmail.com
Requires-Python: >=3.11
Classifier: License :: OSI Approved :: MIT License
Classifier: Programming Language :: Python :: 3
Classifier: Programming Language :: Python :: 3.11
Classifier: Programming Language :: Python :: 3.12
Classifier: Programming Language :: Python :: 3.13
Requires-Dist: pydantic (>=2.11.5,<3.0.0)
Project-URL: Homepage, https://github.com/Carlos-Mesquita/cm-events
Project-URL: Issues, https://github.com/Carlos-Mesquita/cm-events/issues
Project-URL: Repository, https://github.com/Carlos-Mesquita/cm-events
